lorax/__init__.py
lorax/constants.py
lorax/helpers.py
lorax/transform.py
jax_lorax-0.3.1.dist-info/LICENSE
jax_lorax-0.3.1.dist-info/METADATA
jax_lorax-0.3.1.dist-info/WHEEL
jax_lorax-0.3.1.dist-info/RECORD
