Metadata-Version: 2.1
Name: jax-lorax
Version: 0.3.1
Summary: A JAX transform which applies LoRA to arbitrary JAX functions/models
License: MIT
Author: Davis Yoshida
Author-email: dyoshida@ttic.edu
Requires-Python: >=3.8,<4.0
Classifier: License :: OSI Approved :: MIT License
Classifier: Programming Language :: Python :: 3
Classifier: Programming Language :: Python :: 3.8
Classifier: Programming Language :: Python :: 3.9
Classifier: Programming Language :: Python :: 3.10
Classifier: Programming Language :: Python :: 3.11
Classifier: Programming Language :: Python :: 3.12
Requires-Dist: jax (>=0.4.6,<0.5.0)
Requires-Dist: jaxlib (>=0.4.6,<0.5.0)
Requires-Dist: qax (>=0.3.1)
